MANIFEST.in
setup.py
infinityctl/__init__.py
infinityctl/__main__.py
infinityctl/buildchange.py
infinityctl/changemap.py
infinityctl/config.py
infinityctl/startstop.py
infinityctl/status.py
infinityctl/update.py
infinityctl/util.py
infinityctl.egg-info/PKG-INFO
infinityctl.egg-info/SOURCES.txt
infinityctl.egg-info/dependency_links.txt
infinityctl.egg-info/entry_points.txt
infinityctl.egg-info/requires.txt
infinityctl.egg-info/top_level.txt
infinityctl/cfg/config.yml