Metadata-Version: 1.1
Name: infinityctl
Version: 0.7.4
Summary: Infinity Station 13 server management tool
Home-page: https://bitbucket.org/Unicode4all/infinityctl
Author: Unicode4all Foundation
Author-email: anthon@unicode4all.org
License: BSD-3-Clause
Platform: POSIX
Classifier: Development Status :: 4 - Beta
Classifier: Environment :: Console
Classifier: Intended Audience :: System Administrators
Classifier: License :: OSI Approved :: BSD License
Classifier: Operating System :: POSIX
Classifier: Programming Language :: Python :: 3 :: Only
Classifier: Topic :: Utilities
Classifier: Natural Language :: Russian
